monet/__init__.py
monet/batch_correct/__init__.py
monet/batch_correct/mnn.py
monet/cluster/__init__.py
monet/cluster/density.py
monet/cluster/diff_exp.py
monet/cluster/graph.py
monet/cluster/hierarchical.py
monet/cluster/util.py
monet/core/__init__.py
monet/core/exp_matrix.py
monet/core/exp_profile.py
monet/data/RdBu_r_colormap.tsv
monet/data/gene_lists/mitochondrial_human.txt
monet/data/gene_lists/mitochondrial_mouse.txt
monet/data/gene_lists/mitochondrial_zebrafish.txt
monet/data/gene_lists/mt_ribosomal_human.txt
monet/data/gene_lists/ribosomal_human.txt
monet/data/gene_lists/ribosomal_mouse.txt
monet/data/gene_lists/ribosomal_zebrafish.txt
monet/data/test/pbmc_100_compressed_data.pickle
monet/data/test/pbmc_100_decompressed_expression.npz
monet/data/test/pbmc_100_denoised_expression.npz
monet/data/test/pbmc_100_expression.npz
monet/data/test/pbmc_100_expression.tsv
monet/data/test/pbmc_100_pc1_restored_expression.npz
monet/data/test/pbmc_100_pc1_scores.tsv
monet/data/test/pbmc_100_pca_model.pickle
monet/data/test/pbmc_1k_expression.npz
monet/data/test/pbmc_1k_v3_filtered_feature_bc_matrix.tar.gz
monet/denoise/__init__.py
monet/denoise/cli.py
monet/denoise/enhance_model.py
monet/denoise/mcv.py
monet/denoise/util.py
monet/enrichment/__init__.py
monet/enrichment/enrichment_model.py
monet/enrichment/gene_set.py
monet/enrichment/gene_set_collection.py
monet/enrichment/result.py
monet/enrichment/util.py
monet/helper/__init__.py
monet/helper/helper.py
monet/label_transfer/__init__.py
monet/label_transfer/knn.py
monet/latent/__init__.py
monet/latent/compressed_data.py
monet/latent/monet_model.py
monet/latent/pca_model.py
monet/latent/util.py
monet/ontology/__init__.py
monet/ontology/gene_ontology.py
monet/ontology/go_annotation.py
monet/ontology/go_term.py
monet/ontology/util.py
monet/preprocess/__init__.py
monet/preprocess/preprocess.py
monet/preprocess/qc.py
monet/simulate/__init__.py
monet/simulate/sim_enhance.py
monet/util/__init__.py
monet/util/annotations.py
monet-0.3.1.dist-info/LICENSE
monet-0.3.1.dist-info/METADATA
monet-0.3.1.dist-info/WHEEL
monet-0.3.1.dist-info/entry_points.txt
monet-0.3.1.dist-info/top_level.txt
monet-0.3.1.dist-info/RECORD
