Metadata-Version: 2.1
Name: monet
Version: 0.3.1
Summary: Monet: An open-source Python package for analyzing and integrating single-cell RNA-Seq data using PCA-based latent spaces.
Home-page: https://github.com/flo-compbio/monet
Author: Florian Wagner
Author-email: florian.compbio@gmail.com
License: 3-clause BSD
Platform: UNKNOWN
Classifier: Development Status :: 3 - Alpha
Classifier: Intended Audience :: Developers
Classifier: Intended Audience :: Science/Research
Classifier: Topic :: Scientific/Engineering :: Bio-Informatics
Classifier: License :: OSI Approved :: BSD License
Classifier: Programming Language :: Python :: 3.7
Classifier: Programming Language :: Python :: 3.8
Requires-Dist: pandas (>=1.0.3)
Requires-Dist: numpy (>=1.18.1)
Requires-Dist: scipy (>=1.4.1)
Requires-Dist: scikit-learn (>=0.22.1)
Requires-Dist: plotly (>=4.2.1)
Requires-Dist: click (<8,>=7)
Requires-Dist: xlmhg (>=2.5.4)
Requires-Dist: scanpy (>=1.5.1)
Requires-Dist: umap-learn (>=0.4.6)
Provides-Extra: docs
Provides-Extra: tests
Requires-Dist: pytest (>=5.2.1) ; extra == 'tests'
Requires-Dist: pytest-cov (>=2.7.1) ; extra == 'tests'
